example_pk/__init__.py
example_pk/app.py
example_pkg_mq-0.0.1.dist-info/LICENSE
example_pkg_mq-0.0.1.dist-info/METADATA
example_pkg_mq-0.0.1.dist-info/WHEEL
example_pkg_mq-0.0.1.dist-info/top_level.txt
example_pkg_mq-0.0.1.dist-info/RECORD
