Metadata-Version: 2.1
Name: example-pkg-mq
Version: 0.0.1
Summary: Sort description
Home-page: https://github.com/pypa/sampleproject
Author: Example Author
Author-email: author@example.com
Classifier: Programming Language :: Python :: 2
Classifier: License :: OSI Approved :: MIT License
Classifier: Operating System :: OS Independent
License-File: LICENSE
